MANIFEST.in
README.rst
setup.py
SloppyCell/Collections.py
SloppyCell/Ensembles.py
SloppyCell/KeyedList_mod.py
SloppyCell/Model_mod.py
SloppyCell/Observers.py
SloppyCell/OldScipySupport.py
SloppyCell/Optimization.py
SloppyCell/Plotting.py
SloppyCell/Redirector_mod.py
SloppyCell/Residuals.py
SloppyCell/RunInParallel.py
SloppyCell/Subspaces.py
SloppyCell/Utility.py
SloppyCell/__init__.py
SloppyCell/_daskrmodule.c
SloppyCell/daskr.py
SloppyCell/lmopt.py
SloppyCell/misc_c.c
SloppyCell/misc_cmodule.c
SloppyCell.egg-info/PKG-INFO
SloppyCell.egg-info/SOURCES.txt
SloppyCell.egg-info/dependency_links.txt
SloppyCell.egg-info/not-zip-safe
SloppyCell.egg-info/requires.txt
SloppyCell.egg-info/top_level.txt
SloppyCell/ExprManip/AST.py
SloppyCell/ExprManip/Differentiation.py
SloppyCell/ExprManip/Extraction.py
SloppyCell/ExprManip/Py2TeX.py
SloppyCell/ExprManip/Simplify.py
SloppyCell/ExprManip/Substitution.py
SloppyCell/ExprManip/__init__.py
SloppyCell/ReactionNetworks/Components.py
SloppyCell/ReactionNetworks/Dynamics.py
SloppyCell/ReactionNetworks/IO.py
SloppyCell/ReactionNetworks/Network_mod.py
SloppyCell/ReactionNetworks/OptDesign.py
SloppyCell/ReactionNetworks/PerfectData.py
SloppyCell/ReactionNetworks/Plotting.py
SloppyCell/ReactionNetworks/Reactions.py
SloppyCell/ReactionNetworks/RunInParallel.py
SloppyCell/ReactionNetworks/SBMLInterface.py
SloppyCell/ReactionNetworks/Trajectory_mod.py
SloppyCell/ReactionNetworks/__init__.py
SloppyCell/ReactionNetworks/f2py_signatures.pyf
SloppyCell/ReactionNetworks/f2py_signatures_no_derivs.pyf
SloppyCell/ReactionNetworks/mtrand.c
SloppyCell/ReactionNetworks/mtrand.h
SloppyCell/Vandermonde/OptimizeSumDets.py
SloppyCell/Vandermonde/VdmPairwise.py
SloppyCell/Vandermonde/__init__.py
SloppyCell/Vandermonde/clusterScripts.py
SloppyCell/Vandermonde/decompHess.py
ddaskr/daux.c
ddaskr/ddaskr.c
ddaskr/ddaskr_types.h
ddaskr/dlinpk.c
test/test.py
test/test_AST.py
test/test_AlgebraicRules.py
test/test_Constraints.py
test/test_DerivativeCalculators.py
test/test_Differentiation.py
test/test_Ensembles.py
test/test_Events.py
test/test_Extraction.py
test/test_FixedPoints.py
test/test_FreeEnergy.py
test/test_InitialConditions.py
