Metadata-Version: 1.2
Name: SloppyCell
Version: 1.1.0.dev1
Summary: UNKNOWN
Home-page: http://sloppycell.sourceforge.net
Author: Ryan Gutenkunst
Author-email: rgutenk@email.arizona.edu
License: BSD
Keywords: systems biology,sloppy modeling
Platform: UNKNOWN
Classifier: Development Status :: 5 - Production/Stable
Classifier: Environment :: Console
Classifier: Intended Audience :: Science/Research
Classifier: License :: OSI Approved :: BSD License
Classifier: Operating System :: OS Independent
Classifier: Programming Language :: Python :: 2
Classifier: Programming Language :: C
Classifier: Topic :: Scientific/Engineering :: Bio-Informatics
Requires: scipy
Requires: numpy
Requires: matplotlib
Requires-Python: >=2.5, <3
